flickr2kml/__init__.py
flickr2kml/flickr2kml.py
flickr2kml/flickr_api_auth.py
flickr2kml/template_gearth.html
flickr2kml/template_mymaps.html
flickr2kml-4.dist-info/LICENSE
flickr2kml-4.dist-info/METADATA
flickr2kml-4.dist-info/WHEEL
flickr2kml-4.dist-info/entry_points.txt
flickr2kml-4.dist-info/top_level.txt
flickr2kml-4.dist-info/RECORD
