Metadata-Version: 2.1
Name: flickr2kml
Version: 4
Summary: Simple command-line tool to generate a KML from the georeferenced photos in a Flickr album
Home-page: https://github.com/gvellut/flickr2kml
Author: Guilhem Vellut
Author-email: g@vellut.com
License: UNKNOWN
Project-URL: Bug Reports, https://github.com/gvellut/flickr2kml/issues
Project-URL: Source, https://github.com/gvellut/flickr2kml
Keywords: flickr kml geo
Platform: UNKNOWN
Classifier: Development Status :: 4 - Beta
Classifier: Environment :: Console
Classifier: Intended Audience :: Other Audience
Classifier: License :: OSI Approved :: GNU General Public License v3 or later (GPLv3+)
Classifier: Natural Language :: English
Classifier: Programming Language :: Python :: 3
Classifier: Operating System :: OS Independent
Classifier: Topic :: Utilities
Requires-Dist: click (~=7.1.0)
Requires-Dist: colorama (~=0.4.0)
Requires-Dist: termcolor (~=1.1.0)
Requires-Dist: addict (~=2.4.0)
Requires-Dist: click-config-file (~=0.6.0)
Requires-Dist: simplekml (~=1.3.0)
Requires-Dist: flickrapi (~=2.4.0)
Requires-Dist: jinja2 (~=3.0.0)
Requires-Dist: importlib-resources (~=5.2.0)
Requires-Dist: python-dateutil (~=2.8.0)
Provides-Extra: dev
Requires-Dist: black ; extra == 'dev'
Requires-Dist: flake8 ; extra == 'dev'
Requires-Dist: twine ; extra == 'dev'
Requires-Dist: wheel ; extra == 'dev'
